sqlcomposer/__init__.py
sqlcomposer/queries.py
sqlcomposer-2.0.0.dist-info/LICENSE
sqlcomposer-2.0.0.dist-info/METADATA
sqlcomposer-2.0.0.dist-info/WHEEL
sqlcomposer-2.0.0.dist-info/RECORD
