Metadata-Version: 2.1
Name: sqlcomposer
Version: 2.0.0
Summary: Compose raw SQL queries in ORM-like fashion
Home-page: https://git.goral.net.pl/sqlcomposer.git/about
License: GPL-3.0-only
Keywords: sql,query builder
Author: Michal Goral
Author-email: dev@goral.net.pl
Requires-Python: >=3.9,<4.0
Classifier: Development Status :: 4 - Beta
Classifier: Intended Audience :: Developers
Classifier: License :: OSI Approved :: GNU General Public License v3 (GPLv3)
Classifier: Programming Language :: PL/SQL
Classifier: Programming Language :: Python :: 3
Classifier: Programming Language :: Python :: 3.9
Classifier: Programming Language :: Python :: 3.10
Classifier: Programming Language :: Python :: 3.11
Classifier: Topic :: Database
Classifier: Topic :: Software Development :: Libraries
Project-URL: Repository, https://git.goral.net.pl/sqlcomposer.git
